{".class": "MypyFile", "_fullname": "google", "_name": null, "is_stub": false, "names": {".class": "SymbolTable", "OptionValueSpec": {".class": "SymbolTableNode", "kind": "Gdef", "node": {".class": "TypeInfo", "_promote": null, "abstract_attributes": [], "bases": ["google.ValueSpec"], "declared_metaclass": null, "defn": {".class": "ClassDef", "fullname": "google.OptionValueSpec", "metaclass": null, "name": "OptionValueSpec", "type_vars": []}, "flags": [], "fullname": "google.OptionValueSpec", "metaclass_type": null, "module_name": "google", "names": {".class": "SymbolTable", "__init__": {".class": "SymbolTableNode", "kind": "Mdef", "node": {".class": "FuncDef", "arg_kinds": [0, 0], "arg_names": ["self", "arg"], "flags": [], "fullname": "google.OptionValueSpec.__init__", "name": "__init__", "type": null}}, "add_carouselSelect": {".class": "SymbolTableNode", "kind": "Mdef", "node": {".class": "FuncDef", "arg_kinds": [0], "arg_names": ["self"], "flags": [], "fullname": "google.OptionValueSpec.add_carouselSelect", "name": "add_carouselSelect", "type": null}}, "add_list_select": {".class": "SymbolTableNode", "kind": "Mdef", "node": {".class": "FuncDef", "arg_kinds": [0], "arg_names": ["self"], "flags": [], "fullname": "google.OptionValueSpec.add_list_select", "name": "add_list_select", "type": null}}, "add_simple_select": {".class": "SymbolTableNode", "kind": "Mdef", "node": {".class": "FuncDef", "arg_kinds": [0], "arg_names": ["self"], "flags": [], "fullname": "google.OptionValueSpec.add_simple_select", "name": "add_simple_select", "type": null}}}, "tuple_type": null, "type_vars": [], "typeddict_type": null}}, "UserDict": {".class": "SymbolTableNode", "cross_ref": "collections.UserDict", "kind": "Gdef"}, "ValueSpec": {".class": "SymbolTableNode", "kind": "Gdef", "node": {".class": "TypeInfo", "_promote": null, "abstract_attributes": [], "bases": ["builtins.object"], "declared_metaclass": null, "defn": {".class": "ClassDef", "fullname": "google.ValueSpec", "metaclass": null, "name": "ValueSpec", "type_vars": []}, "flags": [], "fullname": "google.ValueSpec", "metaclass_type": null, "module_name": "google", "names": {".class": "SymbolTable", "__init__": {".class": "SymbolTableNode", "kind": "Mdef", "node": {".class": "FuncDef", "arg_kinds": [0, 0], "arg_names": ["self", "arg"], "flags": [], "fullname": "google.ValueSpec.__init__", "name": "__init__", "type": null}}, "arg": {".class": "SymbolTableNode", "implicit": true, "kind": "Mdef", "node": {".class": "Var", "flags": [], "fullname": "google.ValueSpec.arg", "name": "arg", "type": {".class": "AnyType"}}}}, "tuple_type": null, "type_vars": [], "typeddict_type": null}}, "_ApiAiResponse": {".class": "SymbolTableNode", "kind": "Gdef", "node": {".class": "Var", "flags": ["is_ready", "is_suppressed_import"], "fullname": "google._ApiAiResponse", "name": "_ApiAiResponse", "type": {".class": "AnyType"}}}, "_GoogleData": {".class": "SymbolTableNode", "kind": "Gdef", "node": {".class": "TypeInfo", "_promote": null, "abstract_attributes": [], "bases": ["builtins.object"], "declared_metaclass": null, "defn": {".class": "ClassDef", "fullname": "google._GoogleData", "metaclass": null, "name": "_GoogleData", "type_vars": []}, "flags": [], "fullname": "google._GoogleData", "metaclass_type": null, "module_name": "google", "names": {".class": "SymbolTable", "__init__": {".class": "SymbolTableNode", "kind": "Mdef", "node": {".class": "FuncDef", "arg_kinds": [0, 0, 0, 1], "arg_names": ["self", "speech", "display_text", "expect_response"], "flags": [], "fullname": "google._GoogleData.__init__", "name": "__init__", "type": null}}, "display_text": {".class": "SymbolTableNode", "implicit": true, "kind": "Mdef", "node": {".class": "Var", "flags": [], "fullname": "google._GoogleData.display_text", "name": "display_text", "type": {".class": "AnyType"}}}, "expect_response": {".class": "SymbolTableNode", "implicit": true, "kind": "Mdef", "node": {".class": "Var", "flags": [], "fullname": "google._GoogleData.expect_response", "name": "expect_response", "type": {".class": "AnyType"}}}, "input_data": {".class": "SymbolTableNode", "implicit": true, "kind": "Mdef", "node": {".class": "Var", "flags": [], "fullname": "google._GoogleData.input_data", "name": "input_data", "type": {".class": "AnyType"}}}, "intent": {".class": "SymbolTableNode", "implicit": true, "kind": "Mdef", "node": {".class": "Var", "flags": [], "fullname": "google._GoogleData.intent", "name": "intent", "type": {".class": "AnyType"}}}, "load_data": {".class": "SymbolTableNode", "kind": "Mdef", "node": {".class": "FuncDef", "arg_kinds": [0], "arg_names": ["self"], "flags": [], "fullname": "google._GoogleData.load_data", "name": "load_data", "type": null}}, "rich_response": {".class": "SymbolTableNode", "implicit": true, "kind": "Mdef", "node": {".class": "Var", "flags": [], "fullname": "google._GoogleData.rich_response", "name": "rich_response", "type": {".class": "AnyType"}}}, "speech": {".class": "SymbolTableNode", "implicit": true, "kind": "Mdef", "node": {".class": "Var", "flags": [], "fullname": "google._GoogleData.speech", "name": "speech", "type": {".class": "AnyType"}}}, "system_intent": {".class": "SymbolTableNode", "implicit": true, "kind": "Mdef", "node": {".class": "Var", "flags": [], "fullname": "google._GoogleData.system_intent", "name": "system_intent", "type": {".class": "AnyType"}}}}, "tuple_type": null, "type_vars": [], "typeddict_type": null}}, "_RichResponse": {".class": "SymbolTableNode", "kind": "Gdef", "node": {".class": "TypeInfo", "_promote": null, "abstract_attributes": [], "bases": ["builtins.object"], "declared_metaclass": null, "defn": {".class": "ClassDef", "fullname": "google._RichResponse", "metaclass": null, "name": "_RichResponse", "type_vars": []}, "flags": [], "fullname": "google._RichResponse", "metaclass_type": null, "module_name": "google", "names": {".class": "SymbolTable", "__init__": {".class": "SymbolTableNode", "kind": "Mdef", "node": {".class": "FuncDef", "arg_kinds": [0, 0, 0, 0], "arg_names": ["sel", "items", "suggestions", "link_out"], "flags": [], "fullname": "google._RichResponse.__init__", "name": "__init__", "type": null}}, "add_basic_card_item": {".class": "SymbolTableNode", "kind": "Mdef", "node": {".class": "FuncDef", "arg_kinds": [0, 1, 1, 1, 1, 1], "arg_names": ["self", "title", "subtitle", "text", "image", "buttons"], "flags": [], "fullname": "google._RichResponse.add_basic_card_item", "name": "add_basic_card_item", "type": null}}, "add_link_out": {".class": "SymbolTableNode", "kind": "Mdef", "node": {".class": "FuncDef", "arg_kinds": [0, 0], "arg_names": ["dest", "url"], "flags": [], "fullname": "google._RichResponse.add_link_out", "name": "add_link_out", "type": null}}, "add_simple_response_item": {".class": "SymbolTableNode", "kind": "Mdef", "node": {".class": "FuncDef", "arg_kinds": [0, 0, 0], "arg_names": ["self", "speech", "display_text"], "flags": [], "fullname": "google._RichResponse.add_simple_response_item", "name": "add_simple_response_item", "type": null}}, "add_structured_response_item": {".class": "SymbolTableNode", "kind": "Mdef", "node": {".class": "FuncDef", "arg_kinds": [0], "arg_names": ["self"], "flags": [], "fullname": "google._RichResponse.add_structured_response_item", "name": "add_structured_response_item", "type": null}}, "add_suggestion": {".class": "SymbolTableNode", "kind": "Mdef", "node": {".class": "FuncDef", "arg_kinds": [0], "arg_names": ["title"], "flags": [], "fullname": "google._RichResponse.add_suggestion", "name": "add_suggestion", "type": null}}}, "tuple_type": null, "type_vars": [], "typeddict_type": null}}, "_SystemIntent": {".class": "SymbolTableNode", "kind": "Gdef", "node": {".class": "TypeInfo", "_promote": null, "abstract_attributes": [], "bases": ["builtins.object"], "declared_metaclass": null, "defn": {".class": "ClassDef", "fullname": "google._SystemIntent", "metaclass": null, "name": "_SystemIntent", "type_vars": []}, "flags": [], "fullname": "google._SystemIntent", "metaclass_type": null, "module_name": "google", "names": {".class": "SymbolTable", "__init__": {".class": "SymbolTableNode", "kind": "Mdef", "node": {".class": "FuncDef", "arg_kinds": [0, 1, 1], "arg_names": ["self", "intent", "input_value_data"], "flags": [], "fullname": "google._SystemIntent.__init__", "name": "__init__", "type": null}}, "add_simple_select": {".class": "SymbolTableNode", "kind": "Mdef", "node": {".class": "FuncDef", "arg_kinds": [0], "arg_names": ["self"], "flags": [], "fullname": "google._SystemIntent.add_simple_select", "name": "add_simple_select", "type": null}}, "input_value_data": {".class": "SymbolTableNode", "implicit": true, "kind": "Mdef", "node": {".class": "Var", "flags": [], "fullname": "google._SystemIntent.input_value_data", "name": "input_value_data", "type": {".class": "AnyType"}}}, "intent": {".class": "SymbolTableNode", "implicit": true, "kind": "Mdef", "node": {".class": "Var", "flags": [], "fullname": "google._SystemIntent.intent", "name": "intent", "type": {".class": "AnyType"}}}}, "tuple_type": null, "type_vars": [], "typeddict_type": null}}, "__doc__": {".class": "SymbolTableNode", "kind": "Gdef", "node": {".class": "Var", "flags": ["is_ready"], "fullname": "google.__doc__", "name": "__doc__", "type": "builtins.str"}}, "__file__": {".class": "SymbolTableNode", "kind": "Gdef", "node": {".class": "Var", "flags": ["is_ready"], "fullname": "google.__file__", "name": "__file__", "type": "builtins.str"}}, "__name__": {".class": "SymbolTableNode", "kind": "Gdef", "node": {".class": "Var", "flags": ["is_ready"], "fullname": "google.__name__", "name": "__name__", "type": "builtins.str"}}, "__package__": {".class": "SymbolTableNode", "kind": "Gdef", "node": {".class": "Var", "flags": ["is_ready"], "fullname": "google.__package__", "name": "__package__", "type": "builtins.str"}}, "current_app": {".class": "SymbolTableNode", "kind": "Gdef", "node": {".class": "Var", "flags": ["is_ready", "is_suppressed_import"], "fullname": "google.current_app", "name": "current_app", "type": {".class": "AnyType"}}}, "json": {".class": "SymbolTableNode", "kind": "Gdef", "node": {".class": "Var", "flags": ["is_ready", "is_suppressed_import"], "fullname": "google.json", "name": "json", "type": {".class": "AnyType"}}}, "make_response": {".class": "SymbolTableNode", "kind": "Gdef", "node": {".class": "Var", "flags": ["is_ready", "is_suppressed_import"], "fullname": "google.make_response", "name": "make_response", "type": {".class": "AnyType"}}}}, "path": "google.py"}
